<?xml version="1.0" encoding="UTF-8"?><record_update table="sys_atf_schedule_run">
    <sys_atf_schedule_run action="DELETE">
        <active>true</active>
        <browser_name>any</browser_name>
        <browser_version/>
        <description>Run suite 'NeedIt App' on a system with this configuration:
Any browser on any version
Any operating system on any version</description>
        <order>100</order>
        <os_name>any</os_name>
        <os_version/>
        <schedule display_value="My New Schedule">f9b2686a2f7630105979532a2799b6f5</schedule>
        <sys_class_name>sys_atf_schedule_run</sys_class_name>
        <sys_created_by>admin</sys_created_by>
        <sys_created_on>2021-09-27 13:21:39</sys_created_on>
        <sys_id>5cd2ac2a2f7630105979532a2799b6f6</sys_id>
        <sys_mod_count>0</sys_mod_count>
        <sys_name>100</sys_name>
        <sys_package display_value="NeedIt" source="x_58872_needit">6ead8e780f603200cd674f8ce1050ed1</sys_package>
        <sys_policy/>
        <sys_scope display_value="NeedIt">6ead8e780f603200cd674f8ce1050ed1</sys_scope>
        <sys_update_name>sys_atf_schedule_run_5cd2ac2a2f7630105979532a2799b6f6</sys_update_name>
        <sys_updated_by>admin</sys_updated_by>
        <sys_updated_on>2021-09-27 13:21:39</sys_updated_on>
        <test_suite display_value="NeedIt App">bfa3e35a2fb230105979532a2799b6a0</test_suite>
        <watch_list/>
    </sys_atf_schedule_run>
    <sys_update_version action="INSERT_OR_UPDATE">
        <action>DELETE</action>
        <application display_value="NeedIt">6ead8e780f603200cd674f8ce1050ed1</application>
        <file_path/>
        <instance_id>8e9151c5dbe3009452dd2f17d4961930</instance_id>
        <instance_name>dev103015</instance_name>
        <name>sys_atf_schedule_run_5cd2ac2a2f7630105979532a2799b6f6</name>
        <payload><![CDATA[<?xml version="1.0" encoding="UTF-8"?><record_update table="sys_atf_schedule_run"><sys_atf_schedule_run action="INSERT_OR_UPDATE"><active>true</active><browser_name>any</browser_name><browser_version/><description>Run suite 'NeedIt App' on a system with this configuration:
Any browser on any version
Any operating system on any version</description><order>100</order><os_name>any</os_name><os_version/><schedule display_value="My New Schedule">f9b2686a2f7630105979532a2799b6f5</schedule><sys_class_name>sys_atf_schedule_run</sys_class_name><sys_created_by>admin</sys_created_by><sys_created_on>2021-09-27 13:21:39</sys_created_on><sys_id>5cd2ac2a2f7630105979532a2799b6f6</sys_id><sys_mod_count>0</sys_mod_count><sys_name>100</sys_name><sys_package display_value="NeedIt" source="x_58872_needit">6ead8e780f603200cd674f8ce1050ed1</sys_package><sys_policy/><sys_scope display_value="NeedIt">6ead8e780f603200cd674f8ce1050ed1</sys_scope><sys_update_name>sys_atf_schedule_run_5cd2ac2a2f7630105979532a2799b6f6</sys_update_name><sys_updated_by>admin</sys_updated_by><sys_updated_on>2021-09-27 13:21:39</sys_updated_on><test_suite display_value="NeedIt App">bfa3e35a2fb230105979532a2799b6a0</test_suite><watch_list/></sys_atf_schedule_run></record_update>]]></payload>
        <payload_hash>-1552017643</payload_hash>
        <record_name>100</record_name>
        <reverted_from/>
        <source>34131fd62f7230105979532a2799b6d7</source>
        <source_table>sys_update_set</source_table>
        <state>previous</state>
        <sys_created_by>admin</sys_created_by>
        <sys_created_on>2021-09-27 13:21:39</sys_created_on>
        <sys_id>a6d2246a2f7630105979532a2799b6d9</sys_id>
        <sys_mod_count>0</sys_mod_count>
        <sys_recorded_at>17c276b0d460000001</sys_recorded_at>
        <sys_updated_by>admin</sys_updated_by>
        <sys_updated_on>2021-09-27 13:21:39</sys_updated_on>
        <type>Scheduled Suite Run</type>
        <update_guid>eed2246a7b7630103a61548eb3b3d7d8</update_guid>
        <update_guid_history>eed2246a7b7630103a61548eb3b3d7d8:-1552017643</update_guid_history>
    </sys_update_version>
    <sys_metadata_delete action="INSERT_OR_UPDATE">
        <sys_audit_delete/>
        <sys_class_name>sys_metadata_delete</sys_class_name>
        <sys_created_by>admin</sys_created_by>
        <sys_created_on>2021-09-27 13:30:20</sys_created_on>
        <sys_db_object display_value="" name="sys_atf_schedule_run">sys_atf_schedule_run</sys_db_object>
        <sys_id>42d79701b96c46509766a1608d937c99</sys_id>
        <sys_metadata>5cd2ac2a2f7630105979532a2799b6f6</sys_metadata>
        <sys_mod_count>0</sys_mod_count>
        <sys_name>100</sys_name>
        <sys_package display_value="NeedIt" source="x_58872_needit">6ead8e780f603200cd674f8ce1050ed1</sys_package>
        <sys_parent/>
        <sys_policy/>
        <sys_scope display_value="NeedIt">6ead8e780f603200cd674f8ce1050ed1</sys_scope>
        <sys_scope_delete display_value="">94872a8897db403e8ee69a431de2fca4</sys_scope_delete>
        <sys_update_name>sys_atf_schedule_run_5cd2ac2a2f7630105979532a2799b6f6</sys_update_name>
        <sys_update_version display_value="sys_atf_schedule_run_5cd2ac2a2f7630105979532a2799b6f6">a6d2246a2f7630105979532a2799b6d9</sys_update_version>
        <sys_updated_by>admin</sys_updated_by>
        <sys_updated_on>2021-09-27 13:30:20</sys_updated_on>
    </sys_metadata_delete>
</record_update>
